[
    {"surat_id":1, "unit_kerja_penerima":"", "unit_fungsi_penerima":"", "kode_paraf":"", "catatan":"Agar ditindaklanjuti"},
    {"surat_id":2, "unit_kerja_penerima":"", "unit_fungsi_penerima":"", "kode_paraf":"", "catatan":"Untuk dipedomani"},
    {"surat_id":3, "unit_kerja_penerima":"", "unit_fungsi_penerima":"", "kode_paraf":"", "catatan":"Agar dihadiri kegiatan dimaksud, tks"},
    {"surat_id":4, "unit_kerja_penerima":"", "unit_fungsi_penerima":"", "kode_paraf":"", "catatan":"Untuk dipedomani dan ditindaklanjuti, tks"},
    {"surat_id":5, "unit_kerja_penerima":"", "unit_fungsi_penerima":"", "kode_paraf":"", "catatan":"Untuk dipedomani dan infokan kepada semua pegawai provinsi maupun kabupaten, tks"},
    {"surat_id":6, "unit_kerja_penerima":"", "unit_fungsi_penerima":"", "kode_paraf":"", "catatan":"Agar ikut serta dalam briefing online tersebut, tks"},
    {"surat_id":7, "unit_kerja_penerima":"", "unit_fungsi_penerima":"", "kode_paraf":"", "catatan":"Agar ditawarkan kepada yang berminat, tks"},
    {"surat_id":8, "unit_kerja_penerima":"", "unit_fungsi_penerima":"", "kode_paraf":"", "catatan":"Agar diinfokan kepada peserta dan mentor, tks"},
    {"surat_id":9, "unit_kerja_penerima":"", "unit_fungsi_penerima":"", "kode_paraf":"", "catatan":"Kita semua yang diundang untuk berpartisipasi pada kegiatan dimaksud, tks"},
    {"surat_id":10, "unit_kerja_penerima":"", "unit_fungsi_penerima":"", "kode_paraf":"", "catatan":"Untuk dipedomani, tks"},
    {"surat_id":11, "unit_kerja_penerima":"", "unit_fungsi_penerima":"", "kode_paraf":"", "catatan":"Agar ditindaklanjuti, tks"},
    {"surat_id":12, "unit_kerja_penerima":"", "unit_fungsi_penerima":"", "kode_paraf":"", "catatan":"Untuk dipedomani dan tindak lanjuti, tks"},
    {"surat_id":13, "unit_kerja_penerima":"", "unit_fungsi_penerima":"", "kode_paraf":"", "catatan":"Untuk diketahui dan ditunjuk staf utk ikut serta, tks"},
    {"surat_id":14, "unit_kerja_penerima":"", "unit_fungsi_penerima":"", "kode_paraf":"", "catatan":"Untuk dipedomani dan tindak lanjuti, tks"},
    {"surat_id":15, "unit_kerja_penerima":"", "unit_fungsi_penerima":"", "kode_paraf":"", "catatan":"Untuk diketahui dan periksa kelengkapannya"},
    {"surat_id":16, "unit_kerja_penerima":"", "unit_fungsi_penerima":"", "kode_paraf":"", "catatan":"Untuk diketahui dan cek kelengkapannya, tks"},
    {"surat_id":17, "unit_kerja_penerima":"", "unit_fungsi_penerima":"", "kode_paraf":"", "catatan":"Untuk diketahui, tks"},
    {"surat_id":18, "unit_kerja_penerima":"", "unit_fungsi_penerima":"", "kode_paraf":"", "catatan":"Untuk diketahui, tks"},
    {"surat_id":19, "unit_kerja_penerima":"", "unit_fungsi_penerima":"", "kode_paraf":"", "catatan":"Untuk diketahui, tks"},
    {"surat_id":20, "unit_kerja_penerima":"", "unit_fungsi_penerima":"", "kode_paraf":"", "catatan":"Untuk diketahui, tks"},
    {"surat_id":21, "unit_kerja_penerima":"", "unit_fungsi_penerima":"", "kode_paraf":"", "catatan":"Agar dihadiri dan bila perlu bentuk tim internal, tks"},
    {"surat_id":22, "unit_kerja_penerima":"", "unit_fungsi_penerima":"", "kode_paraf":"", "catatan":"Untuk diketahui, tks"},
    {"surat_id":23, "unit_kerja_penerima":"", "unit_fungsi_penerima":"", "kode_paraf":"", "catatan":"Agar dpt berpartisipasi dalam zoom meeting dimaksud, tks"},
    {"surat_id":24, "unit_kerja_penerima":"", "unit_fungsi_penerima":"", "kode_paraf":"", "catatan":"Agar diifokan kepada seluruh pegawai, tks"},
    {"surat_id":25, "unit_kerja_penerima":"", "unit_fungsi_penerima":"", "kode_paraf":"", "catatan":"Untuk diketahui, tks"},
    {"surat_id":26, "unit_kerja_penerima":"", "unit_fungsi_penerima":"", "kode_paraf":"", "catatan":"Untuk dipedomani, tks"},
    {"surat_id":27, "unit_kerja_penerima":"", "unit_fungsi_penerima":"", "kode_paraf":"", "catatan":"Agar ditunjuk peserta untuk mengikuti kegiatan dimaksud, tks"},
    {"surat_id":28, "unit_kerja_penerima":"", "unit_fungsi_penerima":"", "kode_paraf":"", "catatan":"Untuk diketahui, tks"},
    {"surat_id":29, "unit_kerja_penerima":"", "unit_fungsi_penerima":"", "kode_paraf":"", "catatan":"Untuk ditindaklanjuti, tks"},
    {"surat_id":30, "unit_kerja_penerima":"", "unit_fungsi_penerima":"", "kode_paraf":"", "catatan":"Agar diikuti semua pejabat administrator. Tks"},
    {"surat_id":31, "unit_kerja_penerima":"", "unit_fungsi_penerima":"", "kode_paraf":"", "catatan":"Untuk diketahui, tks"},
    {"surat_id":32, "unit_kerja_penerima":"", "unit_fungsi_penerima":"", "kode_paraf":"", "catatan":"Untuk diketahui dan pedomani, tks"},
    {"surat_id":33, "unit_kerja_penerima":"", "unit_fungsi_penerima":"", "kode_paraf":"", "catatan":"Untuk dipedomani dan tindak lanjuti, tks"},
    {"surat_id":34, "unit_kerja_penerima":"", "unit_fungsi_penerima":"", "kode_paraf":"", "catatan":"Agar difasilitasi, tks"},
    {"surat_id":35, "unit_kerja_penerima":"", "unit_fungsi_penerima":"", "kode_paraf":"", "catatan":"Untuk diketahui, tks"},
    {"surat_id":36, "unit_kerja_penerima":"", "unit_fungsi_penerima":"", "kode_paraf":"", "catatan":"Agar berpartisipasi dalam ZM dimaksud, tks"},
    {"surat_id":37, "unit_kerja_penerima":"", "unit_fungsi_penerima":"", "kode_paraf":"", "catatan":"Agar diarsipkan, tks"},
    {"surat_id":38, "unit_kerja_penerima":"", "unit_fungsi_penerima":"", "kode_paraf":"", "catatan":"Untuk diketahui dan pedomani, tks"},
    {"surat_id":39, "unit_kerja_penerima":"", "unit_fungsi_penerima":"", "kode_paraf":"", "catatan":"Untuk diketahui dan kita diskusikan agar bs dikonfirmasikan ke BPS RI, tks"},
    {"surat_id":40, "unit_kerja_penerima":"", "unit_fungsi_penerima":"", "kode_paraf":"", "catatan":"Untuk diketahui dan tindak lanjut, tks"},
    {"surat_id":41, "unit_kerja_penerima":"", "unit_fungsi_penerima":"", "kode_paraf":"", "catatan":"Agar ditunjuk peserta yg akan ikut kegiatan dimaksud, tks"},
    {"surat_id":42, "unit_kerja_penerima":"", "unit_fungsi_penerima":"", "kode_paraf":"", "catatan":"Untuk diketahui dan tindak lanjuti, tks"},
    {"surat_id":43, "unit_kerja_penerima":"", "unit_fungsi_penerima":"", "kode_paraf":"", "catatan":"Untuk dipedomani, tks"},
    {"surat_id":44, "unit_kerja_penerima":"", "unit_fungsi_penerima":"", "kode_paraf":"", "catatan":"Untuk dipedomani, tks"},
    {"surat_id":45, "unit_kerja_penerima":"", "unit_fungsi_penerima":"", "kode_paraf":"", "catatan":"Agar diinfokan kepada pegawai yang berminat, tks"},
    {"surat_id":46, "unit_kerja_penerima":"", "unit_fungsi_penerima":"", "kode_paraf":"", "catatan":"Agar ditindaklanjuti, tks"},
    {"surat_id":47, "unit_kerja_penerima":"", "unit_fungsi_penerima":"", "kode_paraf":"", "catatan":"Untuk diketahui, tks"},
    {"surat_id":48, "unit_kerja_penerima":"", "unit_fungsi_penerima":"", "kode_paraf":"", "catatan":null},
    {"surat_id":49, "unit_kerja_penerima":"", "unit_fungsi_penerima":"", "kode_paraf":"", "catatan":"Agar dilaksanakan, tks"},
    {"surat_id":50, "unit_kerja_penerima":"", "unit_fungsi_penerima":"", "kode_paraf":"", "catatan":null},
    {"surat_id":51, "unit_kerja_penerima":"", "unit_fungsi_penerima":"", "kode_paraf":"", "catatan":"Agar dipahami dan implementasikan, tks"},
    {"surat_id":52, "unit_kerja_penerima":"", "unit_fungsi_penerima":"", "kode_paraf":"", "catatan":"Agar diinfokan kepada ybs, tks"},
    {"surat_id":53, "unit_kerja_penerima":"", "unit_fungsi_penerima":"", "kode_paraf":"", "catatan":null},
    {"surat_id":54, "unit_kerja_penerima":"", "unit_fungsi_penerima":"", "kode_paraf":"", "catatan":"Untuk dipedomani, tks"},
    {"surat_id":55, "unit_kerja_penerima":"", "unit_fungsi_penerima":"", "kode_paraf":"", "catatan":"Untuk dipedomani, tks"},
    {"surat_id":56, "unit_kerja_penerima":"", "unit_fungsi_penerima":"", "kode_paraf":"", "catatan":"Agar dihadiri dan siapkan segala sesuatunya, tks"},
    {"surat_id":57, "unit_kerja_penerima":"", "unit_fungsi_penerima":"", "kode_paraf":"", "catatan":"Untuk diketahui dan infokan kepada calon peserta UPDI, tks"},
    {"surat_id":58, "unit_kerja_penerima":"", "unit_fungsi_penerima":"", "kode_paraf":"", "catatan":"Untuk diketahui dan pedomani, tks"},
    {"surat_id":59, "unit_kerja_penerima":"", "unit_fungsi_penerima":"", "kode_paraf":"", "catatan":"Untuk diketahui dan tindak lanjuti, tks"},
    {"surat_id":60, "unit_kerja_penerima":"", "unit_fungsi_penerima":"", "kode_paraf":"", "catatan":"Untuk diketahui , tks"},
    {"surat_id":61, "unit_kerja_penerima":"", "unit_fungsi_penerima":"", "kode_paraf":"", "catatan":"Untuk diketahui, tks"},
    {"surat_id":62, "unit_kerja_penerima":"", "unit_fungsi_penerima":"", "kode_paraf":"", "catatan":null},
    {"surat_id":63, "unit_kerja_penerima":"", "unit_fungsi_penerima":"", "kode_paraf":"", "catatan":null},
    {"surat_id":64, "unit_kerja_penerima":"", "unit_fungsi_penerima":"", "kode_paraf":"", "catatan":null},
    {"surat_id":65, "unit_kerja_penerima":"", "unit_fungsi_penerima":"", "kode_paraf":"", "catatan":null},
    {"surat_id":66, "unit_kerja_penerima":"", "unit_fungsi_penerima":"", "kode_paraf":"", "catatan":null},
    {"surat_id":67, "unit_kerja_penerima":"", "unit_fungsi_penerima":"", "kode_paraf":"", "catatan":null},
    {"surat_id":68, "unit_kerja_penerima":"", "unit_fungsi_penerima":"", "kode_paraf":"", "catatan":null},
    {"surat_id":69, "unit_kerja_penerima":"", "unit_fungsi_penerima":"", "kode_paraf":"", "catatan":null},
    {"surat_id":70, "unit_kerja_penerima":"", "unit_fungsi_penerima":"", "kode_paraf":"", "catatan":null},
    {"surat_id":71, "unit_kerja_penerima":"", "unit_fungsi_penerima":"", "kode_paraf":"", "catatan":null},
    {"surat_id":72, "unit_kerja_penerima":"", "unit_fungsi_penerima":"", "kode_paraf":"", "catatan":null},
    {"surat_id":73, "unit_kerja_penerima":"", "unit_fungsi_penerima":"", "kode_paraf":"", "catatan":null},
    {"surat_id":74, "unit_kerja_penerima":"", "unit_fungsi_penerima":"", "kode_paraf":"", "catatan":null},
    {"surat_id":75, "unit_kerja_penerima":"", "unit_fungsi_penerima":"", "kode_paraf":"", "catatan":null},
    {"surat_id":76, "unit_kerja_penerima":"", "unit_fungsi_penerima":"", "kode_paraf":"", "catatan":null},
    {"surat_id":77, "unit_kerja_penerima":"", "unit_fungsi_penerima":"", "kode_paraf":"", "catatan":null},
    {"surat_id":78, "unit_kerja_penerima":"", "unit_fungsi_penerima":"", "kode_paraf":"", "catatan":null},
    {"surat_id":79, "unit_kerja_penerima":"", "unit_fungsi_penerima":"", "kode_paraf":"", "catatan":null},
    {"surat_id":80, "unit_kerja_penerima":"", "unit_fungsi_penerima":"", "kode_paraf":"", "catatan":null},
    {"surat_id":81, "unit_kerja_penerima":"", "unit_fungsi_penerima":"", "kode_paraf":"", "catatan":null},
    {"surat_id":82, "unit_kerja_penerima":"", "unit_fungsi_penerima":"", "kode_paraf":"", "catatan":null},
    {"surat_id":83, "unit_kerja_penerima":"", "unit_fungsi_penerima":"", "kode_paraf":"", "catatan":null},
    {"surat_id":84, "unit_kerja_penerima":"", "unit_fungsi_penerima":"", "kode_paraf":"", "catatan":null},
    {"surat_id":85, "unit_kerja_penerima":"", "unit_fungsi_penerima":"", "kode_paraf":"", "catatan":null},
    {"surat_id":86, "unit_kerja_penerima":"", "unit_fungsi_penerima":"", "kode_paraf":"", "catatan":null},
    {"surat_id":87, "unit_kerja_penerima":"", "unit_fungsi_penerima":"", "kode_paraf":"", "catatan":null},
    {"surat_id":88, "unit_kerja_penerima":"", "unit_fungsi_penerima":"", "kode_paraf":"", "catatan":null},
    {"surat_id":89, "unit_kerja_penerima":"", "unit_fungsi_penerima":"", "kode_paraf":"", "catatan":null},
    {"surat_id":90, "unit_kerja_penerima":"", "unit_fungsi_penerima":"", "kode_paraf":"", "catatan":null},
    {"surat_id":91, "unit_kerja_penerima":"", "unit_fungsi_penerima":"", "kode_paraf":"", "catatan":null},
    {"surat_id":92, "unit_kerja_penerima":"", "unit_fungsi_penerima":"", "kode_paraf":"", "catatan":null},
    {"surat_id":93, "unit_kerja_penerima":"", "unit_fungsi_penerima":"", "kode_paraf":"", "catatan":null},
    {"surat_id":94, "unit_kerja_penerima":"", "unit_fungsi_penerima":"", "kode_paraf":"", "catatan":null},
    {"surat_id":95, "unit_kerja_penerima":"", "unit_fungsi_penerima":"", "kode_paraf":"", "catatan":null},
    {"surat_id":96, "unit_kerja_penerima":"", "unit_fungsi_penerima":"", "kode_paraf":"", "catatan":null},
    {"surat_id":97, "unit_kerja_penerima":"", "unit_fungsi_penerima":"", "kode_paraf":"", "catatan":null},
    {"surat_id":98, "unit_kerja_penerima":"", "unit_fungsi_penerima":"", "kode_paraf":"", "catatan":null},
    {"surat_id":99, "unit_kerja_penerima":"", "unit_fungsi_penerima":"", "kode_paraf":"", "catatan":null},
    {"surat_id":100, "unit_kerja_penerima":"", "unit_fungsi_penerima":"", "kode_paraf":"", "catatan":null},
    {"surat_id":101, "unit_kerja_penerima":"", "unit_fungsi_penerima":"", "kode_paraf":"", "catatan":null},
    {"surat_id":102, "unit_kerja_penerima":"", "unit_fungsi_penerima":"", "kode_paraf":"", "catatan":null},
    {"surat_id":103, "unit_kerja_penerima":"", "unit_fungsi_penerima":"", "kode_paraf":"", "catatan":null},
    {"surat_id":104, "unit_kerja_penerima":"", "unit_fungsi_penerima":"", "kode_paraf":"", "catatan":null},
    {"surat_id":105, "unit_kerja_penerima":"", "unit_fungsi_penerima":"", "kode_paraf":"", "catatan":null},
    {"surat_id":106, "unit_kerja_penerima":"", "unit_fungsi_penerima":"", "kode_paraf":"", "catatan":null},
    {"surat_id":107, "unit_kerja_penerima":"", "unit_fungsi_penerima":"", "kode_paraf":"", "catatan":null},
    {"surat_id":108, "unit_kerja_penerima":"", "unit_fungsi_penerima":"", "kode_paraf":"", "catatan":null},
    {"surat_id":109, "unit_kerja_penerima":"", "unit_fungsi_penerima":"", "kode_paraf":"", "catatan":null},
    {"surat_id":110, "unit_kerja_penerima":"", "unit_fungsi_penerima":"", "kode_paraf":"", "catatan":null},
    {"surat_id":111, "unit_kerja_penerima":"", "unit_fungsi_penerima":"", "kode_paraf":"", "catatan":"segera diteruskan ke BPS kab./kota"},
    {"surat_id":112, "unit_kerja_penerima":"", "unit_fungsi_penerima":"", "kode_paraf":"", "catatan":"untuk diketahui"},
    {"surat_id":113, "unit_kerja_penerima":"", "unit_fungsi_penerima":"", "kode_paraf":"", "catatan":"untuk diketahui dan disampaikan kepada pegawai yang menjadi peserta diklat"},
    {"surat_id":114, "unit_kerja_penerima":"", "unit_fungsi_penerima":"", "kode_paraf":"", "catatan":"untuk diketahui dan disampaikan ke peserta pelatihan"},
    {"surat_id":115, "unit_kerja_penerima":"", "unit_fungsi_penerima":"", "kode_paraf":"", "catatan":"segera ditindak lanjuti dan dipersiapkan kelengkapannya"},
    {"surat_id":116, "unit_kerja_penerima":"", "unit_fungsi_penerima":"", "kode_paraf":"", "catatan":"untuk ditindak lanjuti"},
    {"surat_id":117, "unit_kerja_penerima":"", "unit_fungsi_penerima":"", "kode_paraf":"", "catatan":"untuk diketahui"},
    {"surat_id":118, "unit_kerja_penerima":"", "unit_fungsi_penerima":"", "kode_paraf":"", "catatan":"untuk diketahui dan disampaikan kepada pegawai yang menjadi peserta"},
    {"surat_id":119, "unit_kerja_penerima":"", "unit_fungsi_penerima":"", "kode_paraf":"", "catatan":"untuk segera menyampaikan perihal instruksi surat ini"},
    {"surat_id":120, "unit_kerja_penerima":"", "unit_fungsi_penerima":"", "kode_paraf":"", "catatan":"untuk dipergunakan sebagaimana mestinya"},
    {"surat_id":121, "unit_kerja_penerima":"", "unit_fungsi_penerima":"", "kode_paraf":"", "catatan":"untuk diketahui dan diteruskan"},
    {"surat_id":122, "unit_kerja_penerima":"", "unit_fungsi_penerima":"", "kode_paraf":"", "catatan":"untuk diketahui"},
    {"surat_id":123, "unit_kerja_penerima":"", "unit_fungsi_penerima":"", "kode_paraf":"", "catatan":"untuk diketahui dan ditindak lanjuti"},
    {"surat_id":124, "unit_kerja_penerima":"", "unit_fungsi_penerima":"", "kode_paraf":"", "catatan":"untuk diketahui"},
    {"surat_id":125, "unit_kerja_penerima":"", "unit_fungsi_penerima":"", "kode_paraf":"", "catatan":"untuk dipergunakan sebagaimana mestinya"},
    {"surat_id":126, "unit_kerja_penerima":"", "unit_fungsi_penerima":"", "kode_paraf":"", "catatan":"untuk ditindak lanjuti"},
    {"surat_id":127, "unit_kerja_penerima":"", "unit_fungsi_penerima":"", "kode_paraf":"", "catatan":"untuk dipersiapkan kelengkapannya"},
    {"surat_id":128, "unit_kerja_penerima":"", "unit_fungsi_penerima":"", "kode_paraf":"", "catatan":null},
    {"surat_id":129, "unit_kerja_penerima":"", "unit_fungsi_penerima":"", "kode_paraf":"", "catatan":null},
    {"surat_id":130, "unit_kerja_penerima":"", "unit_fungsi_penerima":"", "kode_paraf":"", "catatan":null},
    {"surat_id":131, "unit_kerja_penerima":"", "unit_fungsi_penerima":"", "kode_paraf":"", "catatan":null},
    {"surat_id":132, "unit_kerja_penerima":"", "unit_fungsi_penerima":"", "kode_paraf":"", "catatan":null},
    {"surat_id":133, "unit_kerja_penerima":"", "unit_fungsi_penerima":"", "kode_paraf":"", "catatan":null},
    {"surat_id":134, "unit_kerja_penerima":"", "unit_fungsi_penerima":"", "kode_paraf":"", "catatan":null},
    {"surat_id":135, "unit_kerja_penerima":"", "unit_fungsi_penerima":"", "kode_paraf":"", "catatan":null},
    {"surat_id":136, "unit_kerja_penerima":"", "unit_fungsi_penerima":"", "kode_paraf":"", "catatan":null},
    {"surat_id":137, "unit_kerja_penerima":"", "unit_fungsi_penerima":"", "kode_paraf":"", "catatan":null},
    {"surat_id":138, "unit_kerja_penerima":"", "unit_fungsi_penerima":"", "kode_paraf":"", "catatan":null},
    {"surat_id":139, "unit_kerja_penerima":"", "unit_fungsi_penerima":"", "kode_paraf":"", "catatan":null},
    {"surat_id":140, "unit_kerja_penerima":"", "unit_fungsi_penerima":"", "kode_paraf":"", "catatan":null},
    {"surat_id":141, "unit_kerja_penerima":"", "unit_fungsi_penerima":"", "kode_paraf":"", "catatan":null},
    {"surat_id":142, "unit_kerja_penerima":"", "unit_fungsi_penerima":"", "kode_paraf":"", "catatan":null},
    {"surat_id":143, "unit_kerja_penerima":"", "unit_fungsi_penerima":"", "kode_paraf":"", "catatan":null},
    {"surat_id":144, "unit_kerja_penerima":"", "unit_fungsi_penerima":"", "kode_paraf":"", "catatan":null},
    {"surat_id":145, "unit_kerja_penerima":"", "unit_fungsi_penerima":"", "kode_paraf":"", "catatan":null},
    {"surat_id":146, "unit_kerja_penerima":"", "unit_fungsi_penerima":"", "kode_paraf":"", "catatan":null},
    {"surat_id":147, "unit_kerja_penerima":"", "unit_fungsi_penerima":"", "kode_paraf":"", "catatan":null},
    {"surat_id":148, "unit_kerja_penerima":"", "unit_fungsi_penerima":"", "kode_paraf":"", "catatan":null},
    {"surat_id":149, "unit_kerja_penerima":"", "unit_fungsi_penerima":"", "kode_paraf":"", "catatan":null},
    {"surat_id":150, "unit_kerja_penerima":"", "unit_fungsi_penerima":"", "kode_paraf":"", "catatan":null},
    {"surat_id":151, "unit_kerja_penerima":"", "unit_fungsi_penerima":"", "kode_paraf":"", "catatan":null},
    {"surat_id":152, "unit_kerja_penerima":"", "unit_fungsi_penerima":"", "kode_paraf":"", "catatan":null},
    {"surat_id":153, "unit_kerja_penerima":"", "unit_fungsi_penerima":"", "kode_paraf":"", "catatan":null},
    {"surat_id":154, "unit_kerja_penerima":"", "unit_fungsi_penerima":"", "kode_paraf":"", "catatan":null},
    {"surat_id":155, "unit_kerja_penerima":"", "unit_fungsi_penerima":"", "kode_paraf":"", "catatan":null},
    {"surat_id":156, "unit_kerja_penerima":"", "unit_fungsi_penerima":"", "kode_paraf":"", "catatan":null},
    {"surat_id":157, "unit_kerja_penerima":"", "unit_fungsi_penerima":"", "kode_paraf":"", "catatan":null},
    {"surat_id":158, "unit_kerja_penerima":"", "unit_fungsi_penerima":"", "kode_paraf":"", "catatan":null},
    {"surat_id":159, "unit_kerja_penerima":"", "unit_fungsi_penerima":"", "kode_paraf":"", "catatan":null},
    {"surat_id":160, "unit_kerja_penerima":"", "unit_fungsi_penerima":"", "kode_paraf":"", "catatan":null},
    {"surat_id":161, "unit_kerja_penerima":"", "unit_fungsi_penerima":"", "kode_paraf":"", "catatan":null},
    {"surat_id":162, "unit_kerja_penerima":"", "unit_fungsi_penerima":"", "kode_paraf":"", "catatan":null},
    {"surat_id":163, "unit_kerja_penerima":"", "unit_fungsi_penerima":"", "kode_paraf":"", "catatan":null},
    {"surat_id":164, "unit_kerja_penerima":"", "unit_fungsi_penerima":"", "kode_paraf":"", "catatan":null},
    {"surat_id":165, "unit_kerja_penerima":"", "unit_fungsi_penerima":"", "kode_paraf":"", "catatan":null},
    {"surat_id":166, "unit_kerja_penerima":"", "unit_fungsi_penerima":"", "kode_paraf":"", "catatan":null},
    {"surat_id":167, "unit_kerja_penerima":"", "unit_fungsi_penerima":"", "kode_paraf":"", "catatan":null},
    {"surat_id":168, "unit_kerja_penerima":"", "unit_fungsi_penerima":"", "kode_paraf":"", "catatan":null},
    {"surat_id":169, "unit_kerja_penerima":"", "unit_fungsi_penerima":"", "kode_paraf":"", "catatan":null},
    {"surat_id":170, "unit_kerja_penerima":"", "unit_fungsi_penerima":"", "kode_paraf":"", "catatan":null},
    {"surat_id":171, "unit_kerja_penerima":"", "unit_fungsi_penerima":"", "kode_paraf":"", "catatan":null},
    {"surat_id":172, "unit_kerja_penerima":"", "unit_fungsi_penerima":"", "kode_paraf":"", "catatan":null},
    {"surat_id":173, "unit_kerja_penerima":"", "unit_fungsi_penerima":"", "kode_paraf":"", "catatan":null},
    {"surat_id":174, "unit_kerja_penerima":"", "unit_fungsi_penerima":"", "kode_paraf":"", "catatan":null},
    {"surat_id":175, "unit_kerja_penerima":"", "unit_fungsi_penerima":"", "kode_paraf":"", "catatan":null},
    {"surat_id":176, "unit_kerja_penerima":"", "unit_fungsi_penerima":"", "kode_paraf":"", "catatan":null},
    {"surat_id":177, "unit_kerja_penerima":"", "unit_fungsi_penerima":"", "kode_paraf":"", "catatan":null},
    {"surat_id":178, "unit_kerja_penerima":"", "unit_fungsi_penerima":"", "kode_paraf":"", "catatan":null},
    {"surat_id":179, "unit_kerja_penerima":"", "unit_fungsi_penerima":"", "kode_paraf":"", "catatan":null},
    {"surat_id":180, "unit_kerja_penerima":"", "unit_fungsi_penerima":"", "kode_paraf":"", "catatan":null},
    {"surat_id":181, "unit_kerja_penerima":"", "unit_fungsi_penerima":"", "kode_paraf":"", "catatan":null},
    {"surat_id":182, "unit_kerja_penerima":"", "unit_fungsi_penerima":"", "kode_paraf":"", "catatan":null},
    {"surat_id":183, "unit_kerja_penerima":"", "unit_fungsi_penerima":"", "kode_paraf":"", "catatan":null},
    {"surat_id":184, "unit_kerja_penerima":"", "unit_fungsi_penerima":"", "kode_paraf":"", "catatan":null},
    {"surat_id":185, "unit_kerja_penerima":"", "unit_fungsi_penerima":"", "kode_paraf":"", "catatan":null},
    {"surat_id":186, "unit_kerja_penerima":"", "unit_fungsi_penerima":"", "kode_paraf":"", "catatan":null},
    {"surat_id":187, "unit_kerja_penerima":"", "unit_fungsi_penerima":"", "kode_paraf":"", "catatan":null},
    {"surat_id":188, "unit_kerja_penerima":"", "unit_fungsi_penerima":"", "kode_paraf":"", "catatan":null},
    {"surat_id":189, "unit_kerja_penerima":"", "unit_fungsi_penerima":"", "kode_paraf":"", "catatan":null},
    {"surat_id":190, "unit_kerja_penerima":"", "unit_fungsi_penerima":"", "kode_paraf":"", "catatan":null},
    {"surat_id":191, "unit_kerja_penerima":"", "unit_fungsi_penerima":"", "kode_paraf":"", "catatan":null},
    {"surat_id":192, "unit_kerja_penerima":"", "unit_fungsi_penerima":"", "kode_paraf":"", "catatan":null},
    {"surat_id":193, "unit_kerja_penerima":"", "unit_fungsi_penerima":"", "kode_paraf":"", "catatan":null},
    {"surat_id":194, "unit_kerja_penerima":"", "unit_fungsi_penerima":"", "kode_paraf":"", "catatan":null},
    {"surat_id":195, "unit_kerja_penerima":"", "unit_fungsi_penerima":"", "kode_paraf":"", "catatan":null},
    {"surat_id":196, "unit_kerja_penerima":"", "unit_fungsi_penerima":"", "kode_paraf":"", "catatan":null},
    {"surat_id":197, "unit_kerja_penerima":"", "unit_fungsi_penerima":"", "kode_paraf":"", "catatan":null},
    {"surat_id":198, "unit_kerja_penerima":"", "unit_fungsi_penerima":"", "kode_paraf":"", "catatan":null},
    {"surat_id":199, "unit_kerja_penerima":"", "unit_fungsi_penerima":"", "kode_paraf":"", "catatan":null},
    {"surat_id":200, "unit_kerja_penerima":"", "unit_fungsi_penerima":"", "kode_paraf":"", "catatan":null},
    {"surat_id":201, "unit_kerja_penerima":"", "unit_fungsi_penerima":"", "kode_paraf":"", "catatan":null},
    {"surat_id":202, "unit_kerja_penerima":"", "unit_fungsi_penerima":"", "kode_paraf":"", "catatan":null},
    {"surat_id":203, "unit_kerja_penerima":"", "unit_fungsi_penerima":"", "kode_paraf":"", "catatan":null},
    {"surat_id":204, "unit_kerja_penerima":"", "unit_fungsi_penerima":"", "kode_paraf":"", "catatan":null},
    {"surat_id":205, "unit_kerja_penerima":"", "unit_fungsi_penerima":"", "kode_paraf":"", "catatan":null},
    {"surat_id":206, "unit_kerja_penerima":"", "unit_fungsi_penerima":"", "kode_paraf":"", "catatan":null},
    {"surat_id":207, "unit_kerja_penerima":"", "unit_fungsi_penerima":"", "kode_paraf":"", "catatan":null},
    {"surat_id":208, "unit_kerja_penerima":"", "unit_fungsi_penerima":"", "kode_paraf":"", "catatan":null},
    {"surat_id":209, "unit_kerja_penerima":"", "unit_fungsi_penerima":"", "kode_paraf":"", "catatan":null},
    {"surat_id":210, "unit_kerja_penerima":"", "unit_fungsi_penerima":"", "kode_paraf":"", "catatan":null},
    {"surat_id":211, "unit_kerja_penerima":"", "unit_fungsi_penerima":"", "kode_paraf":"", "catatan":null},
    {"surat_id":212, "unit_kerja_penerima":"", "unit_fungsi_penerima":"", "kode_paraf":"", "catatan":null},
    {"surat_id":213, "unit_kerja_penerima":"", "unit_fungsi_penerima":"", "kode_paraf":"", "catatan":null},
    {"surat_id":214, "unit_kerja_penerima":"", "unit_fungsi_penerima":"", "kode_paraf":"", "catatan":null},
    {"surat_id":215, "unit_kerja_penerima":"", "unit_fungsi_penerima":"", "kode_paraf":"", "catatan":null},
    {"surat_id":216, "unit_kerja_penerima":"", "unit_fungsi_penerima":"", "kode_paraf":"", "catatan":null},
    {"surat_id":217, "unit_kerja_penerima":"", "unit_fungsi_penerima":"", "kode_paraf":"", "catatan":null},
    {"surat_id":218, "unit_kerja_penerima":"", "unit_fungsi_penerima":"", "kode_paraf":"", "catatan":null},
    {"surat_id":219, "unit_kerja_penerima":"", "unit_fungsi_penerima":"", "kode_paraf":"", "catatan":null},
    {"surat_id":220, "unit_kerja_penerima":"", "unit_fungsi_penerima":"", "kode_paraf":"", "catatan":null},
    {"surat_id":221, "unit_kerja_penerima":"", "unit_fungsi_penerima":"", "kode_paraf":"", "catatan":null},
    {"surat_id":222, "unit_kerja_penerima":"", "unit_fungsi_penerima":"", "kode_paraf":"", "catatan":null},
    {"surat_id":223, "unit_kerja_penerima":"", "unit_fungsi_penerima":"", "kode_paraf":"", "catatan":null},
    {"surat_id":224, "unit_kerja_penerima":"", "unit_fungsi_penerima":"", "kode_paraf":"", "catatan":null},
    {"surat_id":225, "unit_kerja_penerima":"", "unit_fungsi_penerima":"", "kode_paraf":"", "catatan":null},
    {"surat_id":226, "unit_kerja_penerima":"", "unit_fungsi_penerima":"", "kode_paraf":"", "catatan":null},
    {"surat_id":227, "unit_kerja_penerima":"", "unit_fungsi_penerima":"", "kode_paraf":"", "catatan":null},
    {"surat_id":228, "unit_kerja_penerima":"", "unit_fungsi_penerima":"", "kode_paraf":"", "catatan":null},
    {"surat_id":229, "unit_kerja_penerima":"", "unit_fungsi_penerima":"", "kode_paraf":"", "catatan":null},
    {"surat_id":230, "unit_kerja_penerima":"", "unit_fungsi_penerima":"", "kode_paraf":"", "catatan":null},
    {"surat_id":231, "unit_kerja_penerima":"", "unit_fungsi_penerima":"", "kode_paraf":"", "catatan":null},
    {"surat_id":232, "unit_kerja_penerima":"", "unit_fungsi_penerima":"", "kode_paraf":"", "catatan":null},
    {"surat_id":233, "unit_kerja_penerima":"", "unit_fungsi_penerima":"", "kode_paraf":"", "catatan":null},
    {"surat_id":234, "unit_kerja_penerima":"", "unit_fungsi_penerima":"", "kode_paraf":"", "catatan":null},
    {"surat_id":235, "unit_kerja_penerima":"", "unit_fungsi_penerima":"", "kode_paraf":"", "catatan":null},
    {"surat_id":236, "unit_kerja_penerima":"", "unit_fungsi_penerima":"", "kode_paraf":"", "catatan":null},
    {"surat_id":237, "unit_kerja_penerima":"", "unit_fungsi_penerima":"", "kode_paraf":"", "catatan":null},
    {"surat_id":238, "unit_kerja_penerima":"", "unit_fungsi_penerima":"", "kode_paraf":"", "catatan":null},
    {"surat_id":239, "unit_kerja_penerima":"", "unit_fungsi_penerima":"", "kode_paraf":"", "catatan":null},
    {"surat_id":240, "unit_kerja_penerima":"", "unit_fungsi_penerima":"", "kode_paraf":"", "catatan":null},
    {"surat_id":241, "unit_kerja_penerima":"", "unit_fungsi_penerima":"", "kode_paraf":"", "catatan":null},
    {"surat_id":242, "unit_kerja_penerima":"", "unit_fungsi_penerima":"", "kode_paraf":"", "catatan":null},
    {"surat_id":243, "unit_kerja_penerima":"", "unit_fungsi_penerima":"", "kode_paraf":"", "catatan":null},
    {"surat_id":244, "unit_kerja_penerima":"", "unit_fungsi_penerima":"", "kode_paraf":"", "catatan":null},
    {"surat_id":245, "unit_kerja_penerima":"", "unit_fungsi_penerima":"", "kode_paraf":"", "catatan":null},
    {"surat_id":246, "unit_kerja_penerima":"", "unit_fungsi_penerima":"", "kode_paraf":"", "catatan":null},
    {"surat_id":247, "unit_kerja_penerima":"", "unit_fungsi_penerima":"", "kode_paraf":"", "catatan":null}
]
